Metadata-Version: 1.0
Name: dada-video
Version: 0.0.9
Summary: Video (mostly ffmpeg) utilities used throughout dada-lake
Home-page: http://globally.ltd
Author: gltd
Author-email: hey@gltd.email
License: UNKNOWN
Platform: UNKNOWN
